fileconsole/__init__.py
fileconsole/console.py
fileconsole-0.1.0.dist-info/METADATA
fileconsole-0.1.0.dist-info/WHEEL
fileconsole-0.1.0.dist-info/top_level.txt
fileconsole-0.1.0.dist-info/RECORD
