Metadata-Version: 2.4
Name: fileconsole
Version: 0.1.0
Summary: For console
Author-email: 刘浩天 <minecraftcaldson@outlook.com>
Requires-Python: >=3.9
